[{"images": [], "type": "genre", "spotify_id": "acoustic", "name": "Acoustic", "uri": "spotify:genre:acoustic"}, {"images": [], "type": "genre", "spotify_id": "afrobeat", "name": "Afrobeat", "uri": "spotify:genre:afrobeat"}, {"images": [], "type": "genre", "spotify_id": "alt-rock", "name": "Alt-rock", "uri": "spotify:genre:alt-rock"}, {"images": [], "type": "genre", "spotify_id": "alternative", "name": "Alternative", "uri": "spotify:genre:alternative"}, {"images": [], "type": "genre", "spotify_id": "ambient", "name": "Ambient", "uri": "spotify:genre:ambient"}, {"images": [], "type": "genre", "spotify_id": "anime", "name": "Anime", "uri": "spotify:genre:anime"}, {"images": [], "type": "genre", "spotify_id": "black-metal", "name": "Black-metal", "uri": "spotify:genre:black-metal"}, {"images": [], "type": "genre", "spotify_id": "bluegrass", "name": "Bluegrass", "uri": "spotify:genre:bluegrass"}, {"images": [], "type": "genre", "spotify_id": "blues", "name": "Blues", "uri": "spotify:genre:blues"}, {"images": [], "type": "genre", "spotify_id": "bossanova", "name": "Bossanova", "uri": "spotify:genre:bossanova"}, {"images": [], "type": "genre", "spotify_id": "brazil", "name": "Brazil", "uri": "spotify:genre:brazil"}, {"images": [], "type": "genre", "spotify_id": "breakbeat", "name": "Breakbeat", "uri": "spotify:genre:breakbeat"}, {"images": [], "type": "genre", "spotify_id": "british", "name": "British", "uri": "spotify:genre:british"}, {"images": [], "type": "genre", "spotify_id": "cantopop", "name": "Cantopop", "uri": "spotify:genre:cantopop"}, {"images": [], "type": "genre", "spotify_id": "chicago-house", "name": "Chicago-house", "uri": "spotify:genre:chicago-house"}, {"images": [], "type": "genre", "spotify_id": "children", "name": "Children", "uri": "spotify:genre:children"}, {"images": [], "type": "genre", "spotify_id": "chill", "name": "Chill", "uri": "spotify:genre:chill"}, {"images": [], "type": "genre", "spotify_id": "classical", "name": "Classical", "uri": "spotify:genre:classical"}, {"images": [], "type": "genre", "spotify_id": "club", "name": "Club", "uri": "spotify:genre:club"}, {"images": [], "type": "genre", "spotify_id": "comedy", "name": "Comedy", "uri": "spotify:genre:comedy"}, {"images": [], "type": "genre", "spotify_id": "country", "name": "Country", "uri": "spotify:genre:country"}, {"images": [], "type": "genre", "spotify_id": "dance", "name": "Dance", "uri": "spotify:genre:dance"}, {"images": [], "type": "genre", "spotify_id": "dancehall", "name": "Dancehall", "uri": "spotify:genre:dancehall"}, {"images": [], "type": "genre", "spotify_id": "death-metal", "name": "Death-metal", "uri": "spotify:genre:death-metal"}, {"images": [], "type": "genre", "spotify_id": "deep-house", "name": "Deep-house", "uri": "spotify:genre:deep-house"}, {"images": [], "type": "genre", "spotify_id": "detroit-techno", "name": "Detroit-techno", "uri": "spotify:genre:detroit-techno"}, {"images": [], "type": "genre", "spotify_id": "disco", "name": "Disco", "uri": "spotify:genre:disco"}, {"images": [], "type": "genre", "spotify_id": "disney", "name": "Disney", "uri": "spotify:genre:disney"}, {"images": [], "type": "genre", "spotify_id": "drum-and-bass", "name": "Drum-and-bass", "uri": "spotify:genre:drum-and-bass"}, {"images": [], "type": "genre", "spotify_id": "dub", "name": "Dub", "uri": "spotify:genre:dub"}, {"images": [], "type": "genre", "spotify_id": "dubstep", "name": "Dubstep", "uri": "spotify:genre:dubstep"}, {"images": [], "type": "genre", "spotify_id": "edm", "name": "Edm", "uri": "spotify:genre:edm"}, {"images": [], "type": "genre", "spotify_id": "electro", "name": "Electro", "uri": "spotify:genre:electro"}, {"images": [], "type": "genre", "spotify_id": "electronic", "name": "Electronic", "uri": "spotify:genre:electronic"}, {"images": [], "type": "genre", "spotify_id": "emo", "name": "Emo", "uri": "spotify:genre:emo"}, {"images": [], "type": "genre", "spotify_id": "folk", "name": "Folk", "uri": "spotify:genre:folk"}, {"images": [], "type": "genre", "spotify_id": "forro", "name": "Forro", "uri": "spotify:genre:forro"}, {"images": [], "type": "genre", "spotify_id": "french", "name": "French", "uri": "spotify:genre:french"}, {"images": [], "type": "genre", "spotify_id": "funk", "name": "Funk", "uri": "spotify:genre:funk"}, {"images": [], "type": "genre", "spotify_id": "garage", "name": "Garage", "uri": "spotify:genre:garage"}, {"images": [], "type": "genre", "spotify_id": "german", "name": "German", "uri": "spotify:genre:german"}, {"images": [], "type": "genre", "spotify_id": "gospel", "name": "Gospel", "uri": "spotify:genre:gospel"}, {"images": [], "type": "genre", "spotify_id": "goth", "name": "Goth", "uri": "spotify:genre:goth"}, {"images": [], "type": "genre", "spotify_id": "grindcore", "name": "Grindcore", "uri": "spotify:genre:grindcore"}, {"images": [], "type": "genre", "spotify_id": "groove", "name": "Groove", "uri": "spotify:genre:groove"}, {"images": [], "type": "genre", "spotify_id": "grunge", "name": "Grunge", "uri": "spotify:genre:grunge"}, {"images": [], "type": "genre", "spotify_id": "guitar", "name": "Guitar", "uri": "spotify:genre:guitar"}, {"images": [], "type": "genre", "spotify_id": "happy", "name": "Happy", "uri": "spotify:genre:happy"}, {"images": [], "type": "genre", "spotify_id": "hard-rock", "name": "Hard-rock", "uri": "spotify:genre:hard-rock"}, {"images": [], "type": "genre", "spotify_id": "hardcore", "name": "Hardcore", "uri": "spotify:genre:hardcore"}, {"images": [], "type": "genre", "spotify_id": "hardstyle", "name": "Hardstyle", "uri": "spotify:genre:hardstyle"}, {"images": [], "type": "genre", "spotify_id": "heavy-metal", "name": "Heavy-metal", "uri": "spotify:genre:heavy-metal"}, {"images": [], "type": "genre", "spotify_id": "hip-hop", "name": "Hip-hop", "uri": "spotify:genre:hip-hop"}, {"images": [], "type": "genre", "spotify_id": "holidays", "name": "Holidays", "uri": "spotify:genre:holidays"}, {"images": [], "type": "genre", "spotify_id": "honky-tonk", "name": "Honky-tonk", "uri": "spotify:genre:honky-tonk"}, {"images": [], "type": "genre", "spotify_id": "house", "name": "House", "uri": "spotify:genre:house"}, {"images": [], "type": "genre", "spotify_id": "idm", "name": "Idm", "uri": "spotify:genre:idm"}, {"images": [], "type": "genre", "spotify_id": "indian", "name": "Indian", "uri": "spotify:genre:indian"}, {"images": [], "type": "genre", "spotify_id": "indie", "name": "Indie", "uri": "spotify:genre:indie"}, {"images": [], "type": "genre", "spotify_id": "indie-pop", "name": "Indie-pop", "uri": "spotify:genre:indie-pop"}, {"images": [], "type": "genre", "spotify_id": "industrial", "name": "Industrial", "uri": "spotify:genre:industrial"}, {"images": [], "type": "genre", "spotify_id": "iranian", "name": "Iranian", "uri": "spotify:genre:iranian"}, {"images": [], "type": "genre", "spotify_id": "j-dance", "name": "J-dance", "uri": "spotify:genre:j-dance"}, {"images": [], "type": "genre", "spotify_id": "j-idol", "name": "J-idol", "uri": "spotify:genre:j-idol"}, {"images": [], "type": "genre", "spotify_id": "j-pop", "name": "J-pop", "uri": "spotify:genre:j-pop"}, {"images": [], "type": "genre", "spotify_id": "j-rock", "name": "J-rock", "uri": "spotify:genre:j-rock"}, {"images": [], "type": "genre", "spotify_id": "jazz", "name": "Jazz", "uri": "spotify:genre:jazz"}, {"images": [], "type": "genre", "spotify_id": "k-pop", "name": "K-pop", "uri": "spotify:genre:k-pop"}, {"images": [], "type": "genre", "spotify_id": "kids", "name": "Kids", "uri": "spotify:genre:kids"}, {"images": [], "type": "genre", "spotify_id": "latin", "name": "Latin", "uri": "spotify:genre:latin"}, {"images": [], "type": "genre", "spotify_id": "latino", "name": "Latino", "uri": "spotify:genre:latino"}, {"images": [], "type": "genre", "spotify_id": "malay", "name": "Malay", "uri": "spotify:genre:malay"}, {"images": [], "type": "genre", "spotify_id": "mandopop", "name": "Mandopop", "uri": "spotify:genre:mandopop"}, {"images": [], "type": "genre", "spotify_id": "metal", "name": "Metal", "uri": "spotify:genre:metal"}, {"images": [], "type": "genre", "spotify_id": "metal-misc", "name": "Metal-misc", "uri": "spotify:genre:metal-misc"}, {"images": [], "type": "genre", "spotify_id": "metalcore", "name": "Metalcore", "uri": "spotify:genre:metalcore"}, {"images": [], "type": "genre", "spotify_id": "minimal-techno", "name": "Minimal-techno", "uri": "spotify:genre:minimal-techno"}, {"images": [], "type": "genre", "spotify_id": "movies", "name": "Movies", "uri": "spotify:genre:movies"}, {"images": [], "type": "genre", "spotify_id": "mpb", "name": "Mpb", "uri": "spotify:genre:mpb"}, {"images": [], "type": "genre", "spotify_id": "new-age", "name": "New-age", "uri": "spotify:genre:new-age"}, {"images": [], "type": "genre", "spotify_id": "new-release", "name": "New-release", "uri": "spotify:genre:new-release"}, {"images": [], "type": "genre", "spotify_id": "opera", "name": "Opera", "uri": "spotify:genre:opera"}, {"images": [], "type": "genre", "spotify_id": "pagode", "name": "Pagode", "uri": "spotify:genre:pagode"}, {"images": [], "type": "genre", "spotify_id": "party", "name": "Party", "uri": "spotify:genre:party"}, {"images": [], "type": "genre", "spotify_id": "philippines-opm", "name": "Philippines-opm", "uri": "spotify:genre:philippines-opm"}, {"images": [], "type": "genre", "spotify_id": "piano", "name": "Piano", "uri": "spotify:genre:piano"}, {"images": [], "type": "genre", "spotify_id": "pop", "name": "Pop", "uri": "spotify:genre:pop"}, {"images": [], "type": "genre", "spotify_id": "pop-film", "name": "Pop-film", "uri": "spotify:genre:pop-film"}, {"images": [], "type": "genre", "spotify_id": "post-dubstep", "name": "Post-dubstep", "uri": "spotify:genre:post-dubstep"}, {"images": [], "type": "genre", "spotify_id": "power-pop", "name": "Power-pop", "uri": "spotify:genre:power-pop"}, {"images": [], "type": "genre", "spotify_id": "progressive-house", "name": "Progressive-house", "uri": "spotify:genre:progressive-house"}, {"images": [], "type": "genre", "spotify_id": "psych-rock", "name": "Psych-rock", "uri": "spotify:genre:psych-rock"}, {"images": [], "type": "genre", "spotify_id": "punk", "name": "Punk", "uri": "spotify:genre:punk"}, {"images": [], "type": "genre", "spotify_id": "punk-rock", "name": "Punk-rock", "uri": "spotify:genre:punk-rock"}, {"images": [], "type": "genre", "spotify_id": "r-n-b", "name": "R-n-b", "uri": "spotify:genre:r-n-b"}, {"images": [], "type": "genre", "spotify_id": "rainy-day", "name": "Rainy-day", "uri": "spotify:genre:rainy-day"}, {"images": [], "type": "genre", "spotify_id": "reggae", "name": "Reggae", "uri": "spotify:genre:reggae"}, {"images": [], "type": "genre", "spotify_id": "reggaeton", "name": "Reggaeton", "uri": "spotify:genre:reggaeton"}, {"images": [], "type": "genre", "spotify_id": "road-trip", "name": "Road-trip", "uri": "spotify:genre:road-trip"}, {"images": [], "type": "genre", "spotify_id": "rock", "name": "Rock", "uri": "spotify:genre:rock"}, {"images": [], "type": "genre", "spotify_id": "rock-n-roll", "name": "Rock-n-roll", "uri": "spotify:genre:rock-n-roll"}, {"images": [], "type": "genre", "spotify_id": "rockabilly", "name": "Rockabilly", "uri": "spotify:genre:rockabilly"}, {"images": [], "type": "genre", "spotify_id": "romance", "name": "Romance", "uri": "spotify:genre:romance"}, {"images": [], "type": "genre", "spotify_id": "sad", "name": "Sad", "uri": "spotify:genre:sad"}, {"images": [], "type": "genre", "spotify_id": "salsa", "name": "Salsa", "uri": "spotify:genre:salsa"}, {"images": [], "type": "genre", "spotify_id": "samba", "name": "Samba", "uri": "spotify:genre:samba"}, {"images": [], "type": "genre", "spotify_id": "sertanejo", "name": "Sertanejo", "uri": "spotify:genre:sertanejo"}, {"images": [], "type": "genre", "spotify_id": "show-tunes", "name": "Show-tunes", "uri": "spotify:genre:show-tunes"}, {"images": [], "type": "genre", "spotify_id": "singer-songwriter", "name": "Singer-songwriter", "uri": "spotify:genre:singer-songwriter"}, {"images": [], "type": "genre", "spotify_id": "ska", "name": "Ska", "uri": "spotify:genre:ska"}, {"images": [], "type": "genre", "spotify_id": "sleep", "name": "Sleep", "uri": "spotify:genre:sleep"}, {"images": [], "type": "genre", "spotify_id": "songwriter", "name": "Songwriter", "uri": "spotify:genre:songwriter"}, {"images": [], "type": "genre", "spotify_id": "soul", "name": "Soul", "uri": "spotify:genre:soul"}, {"images": [], "type": "genre", "spotify_id": "soundtracks", "name": "Soundtracks", "uri": "spotify:genre:soundtracks"}, {"images": [], "type": "genre", "spotify_id": "spanish", "name": "Spanish", "uri": "spotify:genre:spanish"}, {"images": [], "type": "genre", "spotify_id": "study", "name": "Study", "uri": "spotify:genre:study"}, {"images": [], "type": "genre", "spotify_id": "summer", "name": "Summer", "uri": "spotify:genre:summer"}, {"images": [], "type": "genre", "spotify_id": "swedish", "name": "Swedish", "uri": "spotify:genre:swedish"}, {"images": [], "type": "genre", "spotify_id": "synth-pop", "name": "Synth-pop", "uri": "spotify:genre:synth-pop"}, {"images": [], "type": "genre", "spotify_id": "tango", "name": "Tango", "uri": "spotify:genre:tango"}, {"images": [], "type": "genre", "spotify_id": "techno", "name": "Techno", "uri": "spotify:genre:techno"}, {"images": [], "type": "genre", "spotify_id": "trance", "name": "Trance", "uri": "spotify:genre:trance"}, {"images": [], "type": "genre", "spotify_id": "trip-hop", "name": "Trip-hop", "uri": "spotify:genre:trip-hop"}, {"images": [], "type": "genre", "spotify_id": "turkish", "name": "Turkish", "uri": "spotify:genre:turkish"}, {"images": [], "type": "genre", "spotify_id": "work-out", "name": "Work-out", "uri": "spotify:genre:work-out"}, {"images": [], "type": "genre", "spotify_id": "world-music", "name": "World-music", "uri": "spotify:genre:world-music"}]
